w0mb0c0mb0/__init__.py
w0mb0c0mb0-0.0.1.dist-info/METADATA
w0mb0c0mb0-0.0.1.dist-info/WHEEL
w0mb0c0mb0-0.0.1.dist-info/RECORD
