Metadata-Version: 2.1
Name: w0mb0c0mb0
Version: 0.0.1
Summary: combination functions
Project-URL: Homepage, https://github.com/Youltaid48/w0mb0c0mb0
Author-email: Youltaid48 <dnc@w0mb0c0mb0.org>
Classifier: Operating System :: OS Independent
Classifier: Programming Language :: Python :: 3
Requires-Python: >=3.8
